scattertext/AsianNLP.py
scattertext/AutoTermSelector.py
scattertext/CLI.py
scattertext/CSRMatrixTools.py
scattertext/CategoryColorAssigner.py
scattertext/Common.py
scattertext/Corpus.py
scattertext/CorpusDF.py
scattertext/CorpusFromFeatureDict.py
scattertext/CorpusFromPandas.py
scattertext/CorpusFromParsedDocuments.py
scattertext/CorpusFromScikit.py
scattertext/CorpusFromTermFrequencies.py
scattertext/CorpusWithoutCategoriesFromParsedDocuments.py
scattertext/DataFrameCorpus.py
scattertext/DeployedClassifier.py
scattertext/DocsAndLabelsFromCorpus.py
scattertext/FeatureOuput.py
scattertext/Formatter.py
scattertext/OffsetCorpus.py
scattertext/OffsetCorpusFactory.py
scattertext/OneClassScatterChart.py
scattertext/PValGetter.py
scattertext/ParsedCorpus.py
scattertext/PriorFactory.py
scattertext/SampleCorpora.py
scattertext/SampleLexicons.py
scattertext/Scalers.py
scattertext/ScatterChart.py
scattertext/ScatterChartData.py
scattertext/ScatterChartExplorer.py
scattertext/TermCategoryFrequencies.py
scattertext/TermDocMatrix.py
scattertext/TermDocMatrixFactory.py
scattertext/TermDocMatrixFilter.py
scattertext/TermDocMatrixFromFrequencies.py
scattertext/TermDocMatrixFromPandas.py
scattertext/TermDocMatrixFromScikit.py
scattertext/TermDocMatrixWithoutCategories.py
scattertext/WhitespaceNLP.py
scattertext/__init__.py
scattertext/util.py
scattertext/all_category_scorers/__init__.py
scattertext/all_category_scorers/all_category_scorer.py
scattertext/all_category_scorers/all_category_term_scorer.py
scattertext/all_category_scorers/gmean_l2_freq_associator.py
scattertext/categorygrouping/__init__.py
scattertext/categorygrouping/characteristic_embedder_base.py
scattertext/categorygrouping/characteristic_grouper.py
scattertext/categorygrouping/rank_embedder.py
scattertext/categoryprojector/CategoryProjection.py
scattertext/categoryprojector/CategoryProjector.py
scattertext/categoryprojector/CategoryProjectorEvaluator.py
scattertext/categoryprojector/OptimalProjection.py
scattertext-0.2.2.dist-info/LICENSE
scattertext-0.2.2.dist-info/METADATA
scattertext-0.2.2.dist-info/WHEEL
scattertext-0.2.2.dist-info/entry_points.txt
scattertext-0.2.2.dist-info/top_level.txt
scattertext-0.2.2.dist-info/RECORD
